hypeban/__init__.py
hypeban/hypeban.py
hypeban-0.0.3.dist-info/LICENSE
hypeban-0.0.3.dist-info/METADATA
hypeban-0.0.3.dist-info/WHEEL
hypeban-0.0.3.dist-info/top_level.txt
hypeban-0.0.3.dist-info/RECORD
