Metadata-Version: 2.1
Name: hypeban
Version: 0.0.3
Summary: A utitlity for date operations
Home-page: https://github.com/Bupper420/hypeban
Author: Bupper
Author-email: spidy1576@outlook.com
License: UNKNOWN
Project-URL: Bug Tracker, https://github.com/Bupper420/hypeban/issues
Platform: UNKNOWN
Classifier: Programming Language :: Python :: 3
Classifier: License :: OSI Approved :: GNU General Public License v3 (GPLv3)
Classifier: Operating System :: OS Independent
Requires-Python: >=3.6
License-File: LICENSE
